traccuracy/__init__.py
traccuracy/_run_metrics.py
traccuracy/_tracking_graph.py
traccuracy/cli.py
traccuracy/utils.py
traccuracy/loaders/__init__.py
traccuracy/loaders/_ctc.py
traccuracy/loaders/_geff.py
traccuracy/loaders/_point.py
traccuracy/matchers/__init__.py
traccuracy/matchers/_base.py
traccuracy/matchers/_compute_overlap.py
traccuracy/matchers/_ctc.py
traccuracy/matchers/_iou.py
traccuracy/matchers/_matched.py
traccuracy/matchers/_point.py
traccuracy/matchers/_point_seg.py
traccuracy/metrics/__init__.py
traccuracy/metrics/_base.py
traccuracy/metrics/_basic.py
traccuracy/metrics/_cca.py
traccuracy/metrics/_chota.py
traccuracy/metrics/_complete_tracks.py
traccuracy/metrics/_ctc.py
traccuracy/metrics/_divisions.py
traccuracy/metrics/_results.py
traccuracy/metrics/_track_overlap.py
traccuracy/track_errors/__init__.py
traccuracy/track_errors/_basic.py
traccuracy/track_errors/_ctc.py
traccuracy/track_errors/_divisions.py
traccuracy-0.4.3.dist-info/licenses/LICENSE
traccuracy-0.4.3.dist-info/METADATA
traccuracy-0.4.3.dist-info/WHEEL
traccuracy-0.4.3.dist-info/entry_points.txt
traccuracy-0.4.3.dist-info/top_level.txt
traccuracy-0.4.3.dist-info/RECORD
