Metadata-Version: 2.4
Name: traccuracy
Version: 0.4.3
Summary: Utilities for computing common accuracy metrics on cell tracking challenge solutions with ground truth
Author-email: Draga Doncila Pop <draga.doncilapop1@monash.edu>, Caroline Malin-Mayor <cmalinmayor@gmail.com>, Morgan Schwartz <msschwartz21@gmail.com>
License: BSD 3-Clause License
Project-URL: homepage, https://github.com/live-image-tracking-tools/traccuracy
Project-URL: repository, https://github.com/live-image-tracking-tools/traccuracy
Project-URL: documentation, https://traccuracy.readthedocs.io/
Classifier: Development Status :: 3 - Alpha
Classifier: License :: OSI Approved :: BSD License
Classifier: Natural Language :: English
Classifier: Programming Language :: Python :: 3
Classifier: Programming Language :: Python :: 3.10
Classifier: Programming Language :: Python :: 3.11
Classifier: Programming Language :: Python :: 3.12
Classifier: Programming Language :: Python :: 3.13
Classifier: Typing :: Typed
Requires-Python: >=3.10
License-File: LICENSE
Requires-Dist: click<8.2.0
Requires-Dist: numpy
Requires-Dist: networkx
Requires-Dist: pandas
Requires-Dist: tifffile
Requires-Dist: imagecodecs
Requires-Dist: scikit-image
Requires-Dist: tqdm
Requires-Dist: typer
Requires-Dist: numba
Requires-Dist: pyarrow
Requires-Dist: scipy
Requires-Dist: skan>=0.13
Requires-Dist: geff>=1.0
Requires-Dist: pylapy[sparse]>=1.0
Provides-Extra: test
Requires-Dist: pytest>=6.0; extra == "test"
Requires-Dist: pytest-cov; extra == "test"
Requires-Dist: pytest-benchmark; extra == "test"
Requires-Dist: pytest-timeout; extra == "test"
Requires-Dist: tabulate; extra == "test"
Provides-Extra: dev
Requires-Dist: ipython; extra == "dev"
Requires-Dist: pdbpp; extra == "dev"
Requires-Dist: pre-commit; extra == "dev"
Requires-Dist: ruff; extra == "dev"
Requires-Dist: traccuracy[test]; extra == "dev"
Requires-Dist: traccuracy[docs]; extra == "dev"
Requires-Dist: traccuracy[typing]; extra == "dev"
Provides-Extra: docs
Requires-Dist: myst-nb<2,>=1.2.0; extra == "docs"
Requires-Dist: sphinx-autoapi==3.0.0; extra == "docs"
Requires-Dist: sphinx-click<7,>=6.0.0; extra == "docs"
Requires-Dist: sphinx-rtd-theme<4,>=3.0.1; extra == "docs"
Requires-Dist: sphinx<8,>=7.4.7; extra == "docs"
Requires-Dist: matplotlib; extra == "docs"
Requires-Dist: jupytext<2,>=1.16.7; extra == "docs"
Requires-Dist: nbsphinx-link==1.3.0; extra == "docs"
Requires-Dist: nbsphinx==0.9.3; extra == "docs"
Requires-Dist: docutils==0.20.*; extra == "docs"
Requires-Dist: astroid<4.0; extra == "docs"
Provides-Extra: covreport
Requires-Dist: traccuracy[test]; extra == "covreport"
Requires-Dist: seaborn; extra == "covreport"
Provides-Extra: typing
Requires-Dist: mypy; extra == "typing"
Requires-Dist: types-networkx; extra == "typing"
Requires-Dist: scipy-stubs; extra == "typing"
Requires-Dist: pandas-stubs; extra == "typing"
Requires-Dist: types-tqdm; extra == "typing"
Dynamic: license-file
